__init__.py
farkle_simulation/__init__.py
farkle_simulation/pipeline.py
farkle_simulation/components/__init__.py
farkle_simulation/components/architecture.py
farkle_simulation/components/max_score.jsonl
farkle_simulation/components/simple_action_reward_state_dict.pt
farkle_simulation/components/simple_farkle_rl.py
farkle_simulation/components/simulation.py
farkle_simulation/components/strategy.py
farkle_simulation/components/utils.py
farkle_simulation-0.1.0.dist-info/licenses/LICENSE
farkle_simulation-0.1.0.dist-info/METADATA
farkle_simulation-0.1.0.dist-info/WHEEL
farkle_simulation-0.1.0.dist-info/top_level.txt
farkle_simulation-0.1.0.dist-info/RECORD
