Metadata-Version: 2.4
Name: farkle-simulation
Version: 0.1.0
Summary: Simulating two-player Farkle with different strategies.
Author-email: Ronen Huang <ronenhuang24@gmail.com>
Project-URL: Homepage, https://github.com/ronenh24/farkle_simulation
Project-URL: Issues, https://github.com/ronenh24/farkle_simulation/issues
Classifier: Programming Language :: Python :: 3
Classifier: Operating System :: OS Independent
Classifier: License :: OSI Approved :: MIT License
Requires-Python: >=3.9
License-File: LICENSE
Requires-Dist: optuna
Requires-Dist: orjson
Requires-Dist: scipy
Requires-Dist: seaborn
Requires-Dist: torch
Dynamic: license-file
